text_to_number/__init__.py
text_to_number/core.py
text_to_number-0.1.2.dist-info/METADATA
text_to_number-0.1.2.dist-info/WHEEL
text_to_number-0.1.2.dist-info/licenses/LICENSE
text_to_number-0.1.2.dist-info/RECORD
