Metadata-Version: 2.3
Name: text-to-number
Version: 0.1.2
Summary: A package to convert text numbers into integers.
Project-URL: homepage, https://github.com/soham-padia/textToInt
Project-URL: repository, https://github.com/soham-padia/textToInt
Project-URL: documentation, https://github.com/soham-padia/textToInt/wiki
Author-email: Soham Padia <sohampadia10@gmail.com>
License: MIT License
License-File: LICENSE
Classifier: Development Status :: 3 - Alpha
Classifier: Intended Audience :: Developers
Classifier: License :: OSI Approved :: MIT License
Classifier: Programming Language :: Python :: 3
Classifier: Programming Language :: Python :: 3 :: Only
Classifier: Topic :: Utilities
Requires-Python: >=3.6
Provides-Extra: test
Requires-Dist: pytest>=6.0; extra == 'test'
Requires-Dist: tox>=3.21; extra == 'test'
